date_assistant/__init__.py
date_assistant/classes.py
date_assistant/date_formats.py
date_assistant/utils.py
date_assistant-0.11.2.dist-info/LICENSE
date_assistant-0.11.2.dist-info/WHEEL
date_assistant-0.11.2.dist-info/METADATA
date_assistant-0.11.2.dist-info/RECORD
