Metadata-Version: 2.1
Name: date-assistant
Version: 0.11.2
Summary: 🗓 Classes and functions with intuitive names for common dates operations
Home-page: https://github.com/jalvaradosegura/date-assistant
License: MIT
Author: Jorge Alvarado
Author-email: alvaradosegurajorge@gmail.com
Requires-Python: >=3.8,<4.0
Classifier: License :: OSI Approved :: MIT License
Classifier: Programming Language :: Python :: 3
Classifier: Programming Language :: Python :: 3.8
Classifier: Programming Language :: Python :: 3.9
Requires-Dist: pre-commit (>=2.15.0,<3.0.0)
Requires-Dist: python-dateutil (>=2.8.2,<3.0.0)
Project-URL: Repository, https://github.com/jalvaradosegura/date-assistant
